{
  "$schema": "./node_modules/@angular/service-worker/config/schema.json",
  "index": "/index.html",
  "assetGroups": [
    {
      "name": "app",
      "installMode": "prefetch",
      "resources": {
        "files": [
          "/favicon.ico",
          "/index.html",
          "/manifest.webmanifest",
          "/*.css",
          "/*.js"
        ]
      }
    },
    {
      "name": "icons",
      "installMode": "prefetch", // Download as soon as possible, may cause big net usage
      "updateMode": "prefetch", // Use cached version
      "resources": {
        "files": [
          "/svg/*.svg", // Path or template for your icons (Fetches all of it)
          "/svg/concrete.svg" // You may use concrete ones only
        ]
      }
},
    
    {
      "name": "assets",
      "installMode": "lazy",
      "updateMode": "prefetch",
      "resources": {
        "files": [
          "/assets/**",
          "/*.(eot|svg|cur|jpg|png|webp|gif|otf|ttf|woff|woff2|ani)"
        ]
      }
    }
  ]
}
